general_tools_winni/__init__.py
general_tools_winni/general_tools.py
general_tools_winni-1.0.1.dist-info/METADATA
general_tools_winni-1.0.1.dist-info/WHEEL
general_tools_winni-1.0.1.dist-info/licenses/LICENSE
general_tools_winni-1.0.1.dist-info/RECORD
