Metadata-Version: 2.1
Name: general_tools_winni
Version: 1.0.1
Summary: Useful scripts
Author-email: Winfried Körting <wk@pmedien.com>
License-File: LICENSE
Classifier: License :: OSI Approved :: MIT License
Classifier: Operating System :: OS Independent
Classifier: Programming Language :: Python :: 3
Requires-Python: >=3.7
